MANIFEST.in
README.md
setup.py
bmk_ocean_stars.egg-info/PKG-INFO
bmk_ocean_stars.egg-info/SOURCES.txt
bmk_ocean_stars.egg-info/dependency_links.txt
bmk_ocean_stars.egg-info/entry_points.txt
bmk_ocean_stars.egg-info/requires.txt
bmk_ocean_stars.egg-info/top_level.txt
bmkos/__init__.py
bmkos/__main__.py
bmkos/anno_gene.py
bmkos/cluster_umi.py
bmkos/extract_barcode.py
bmkos/gene_expression.py
bmkos/pipeline.py
bmkos/plotQC.py
bmkos/report/cell_template.html
bmkos/report/spatial_template.html
bmkos/sequence/bc1.sorted.fa
bmkos/sequence/bc1.sorted.txt
bmkos/sequence/bc1_all.fa
bmkos/sequence/bc2.sorted.fa
bmkos/sequence/bc2.sorted.txt
bmkos/sequence/bc2_all.fa
bmkos/sequence/bc3.sorted.fa
bmkos/sequence/bc3.sorted.txt
bmkos/sequence/bc3_all.fa
bmkos/sequence/link1.fa
bmkos/sequence/polyT.fa
bmkos/sequence/read1.fa
bmkos/sequence/ssp.fa