Metadata-Version: 2.1
Name: bmk-ocean-stars
Version: 0.6.8
Summary: Analysis of nanopore sequencing data of single cell.
Home-page: https://github.com/wangjianshou/bmk-ocean-stars
Author: Wang Jianshou
Author-email: wangjs@biomarker.com.cn
License: UNKNOWN
Platform: UNKNOWN
Classifier: Development Status :: 3 - Alpha
Classifier: Operating System :: POSIX :: Linux
Classifier: Programming Language :: Python :: 3.9
Classifier: Programming Language :: Python :: 3.8
Requires-Python: >=3.8, <3.10
